PySSHHelper/__init__.py
PySSHHelper/_version.py
PySSHHelper/connection.py
pysshhelper-0.1.2.dist-info/LICENSE
pysshhelper-0.1.2.dist-info/METADATA
pysshhelper-0.1.2.dist-info/WHEEL
pysshhelper-0.1.2.dist-info/RECORD
