Metadata-Version: 2.1
Name: PySSHHelper
Version: 0.1.2
Summary: Python library for executing commands interactively over SSH including sudo su - priveleges
License: MIT
Author: Max
Author-email: PySSHHelper@proton.me
Requires-Python: >=3.8,<4.0
Classifier: License :: OSI Approved :: MIT License
Classifier: Operating System :: OS Independent
Classifier: Programming Language :: Python
Classifier: Programming Language :: Python :: 3
Classifier: Programming Language :: Python :: 3.8
Classifier: Programming Language :: Python :: 3.9
Classifier: Programming Language :: Python :: 3.10
Classifier: Programming Language :: Python :: 3.11
Classifier: Programming Language :: Python :: 3.12
Classifier: Programming Language :: Python :: 3 :: Only
Classifier: Topic :: Internet
Classifier: Topic :: Security :: Cryptography
Requires-Dist: paramiko (>=3.4,<4.0)
Project-URL: Homepage, https://github.com/xeonvs/PySSHHelper
Project-URL: Issues, https://github.com/xeonvs/PySSHHelper/issues
